setup.py
gaeflickrlib/__init__.py
gaeflickrlib/exceptionhandlers.py
gaeflickrlib/helpers.py
gaeflickrlib/models.py
gaeflickrlib.egg-info/PKG-INFO
gaeflickrlib.egg-info/SOURCES.txt
gaeflickrlib.egg-info/dependency_links.txt
gaeflickrlib.egg-info/requires.txt
gaeflickrlib.egg-info/top_level.txt