Metadata-Version: 1.0
Name: gaeflickrlib
Version: 0.5
Summary: Flickr API kit for Google App Engine
Home-page: http://www.geoffreyspear.com/gaeflickrlib/index.html
Author: Geoffrey Spear
Author-email: geoffspear@gmail.com
License: UNKNOWN
Keywords: flickr,google-app-engine
Platform: UNKNOWN
Classifier: Development Status :: 2 - Pre-Alpha
Classifier: Intended Audience :: Developers
Classifier: License :: OSI Approved :: BSD License
Classifier: Programming Language :: Python :: 2.5
Classifier: Topic :: Software Development :: Libraries :: Python Modules
